more_cli/__init__.py
more_cli/main.py
more_cli-1.1.0.dist-info/entry_points.txt
more_cli-1.1.0.dist-info/WHEEL
more_cli-1.1.0.dist-info/METADATA
more_cli-1.1.0.dist-info/RECORD
